setup.py
Cryptodome/__init__.py
Cryptodome/Cipher/AES.py
Cryptodome/Cipher/ARC2.py
Cryptodome/Cipher/ARC4.py
Cryptodome/Cipher/Blowfish.py
Cryptodome/Cipher/CAST.py
Cryptodome/Cipher/ChaCha20.py
Cryptodome/Cipher/ChaCha20_Poly1305.py
Cryptodome/Cipher/DES.py
Cryptodome/Cipher/DES3.py
Cryptodome/Cipher/PKCS1_OAEP.py
Cryptodome/Cipher/PKCS1_v1_5.py
Cryptodome/Cipher/Salsa20.py
Cryptodome/Cipher/_EKSBlowfish.py
Cryptodome/Cipher/__init__.py
Cryptodome/Cipher/_mode_cbc.py
Cryptodome/Cipher/_mode_ccm.py
Cryptodome/Cipher/_mode_cfb.py
Cryptodome/Cipher/_mode_ctr.py
Cryptodome/Cipher/_mode_eax.py
Cryptodome/Cipher/_mode_ecb.py
Cryptodome/Cipher/_mode_gcm.py
Cryptodome/Cipher/_mode_ocb.py
Cryptodome/Cipher/_mode_ofb.py
Cryptodome/Cipher/_mode_openpgp.py
Cryptodome/Cipher/_mode_siv.py
Cryptodome/Hash/BLAKE2b.py
Cryptodome/Hash/BLAKE2s.py
Cryptodome/Hash/CMAC.py
Cryptodome/Hash/HMAC.py
Cryptodome/Hash/KMAC128.py
Cryptodome/Hash/KMAC256.py
Cryptodome/Hash/KangarooTwelve.py
Cryptodome/Hash/MD2.py
Cryptodome/Hash/MD4.py
Cryptodome/Hash/MD5.py
Cryptodome/Hash/Poly1305.py
Cryptodome/Hash/RIPEMD.py
Cryptodome/Hash/RIPEMD160.py
Cryptodome/Hash/SHA.py
Cryptodome/Hash/SHA1.py
Cryptodome/Hash/SHA224.py
Cryptodome/Hash/SHA256.py
Cryptodome/Hash/SHA384.py
Cryptodome/Hash/SHA3_224.py
Cryptodome/Hash/SHA3_256.py
Cryptodome/Hash/SHA3_384.py
Cryptodome/Hash/SHA3_512.py
Cryptodome/Hash/SHA512.py
Cryptodome/Hash/SHAKE128.py
Cryptodome/Hash/SHAKE256.py
Cryptodome/Hash/TupleHash128.py
Cryptodome/Hash/TupleHash256.py
Cryptodome/Hash/__init__.py
Cryptodome/Hash/cSHAKE128.py
Cryptodome/Hash/cSHAKE256.py
Cryptodome/Hash/keccak.py
Cryptodome/IO/PEM.py
Cryptodome/IO/PKCS8.py
Cryptodome/IO/_PBES.py
Cryptodome/IO/__init__.py
Cryptodome/Math/Numbers.py
Cryptodome/Math/Primality.py
Cryptodome/Math/_IntegerBase.py
Cryptodome/Math/_IntegerCustom.py
Cryptodome/Math/_IntegerGMP.py
Cryptodome/Math/_IntegerNative.py
Cryptodome/Math/__init__.py
Cryptodome/Protocol/KDF.py
Cryptodome/Protocol/SecretSharing.py
cryptocode.py.egg-info/PKG-INFO
cryptocode.py.egg-info/SOURCES.txt
cryptocode.py.egg-info/dependency_links.txt
cryptocode.py.egg-info/entry_points.txt
cryptocode.py.egg-info/requires.txt
cryptocode.py.egg-info/top_level.txt