Metadata-Version: 2.1
Name: cryptocode.py
Version: 2.6
Summary: [我是一隻小貓]
Home-page: UNKNOWN
Author: moon-start
Author-email: moon-start@gmail.com
License: LGPL
Platform: UNKNOWN
